whisper_cpp_client/WhisperCppClient.py
whisper_cpp_client/__init__.py
whisper_cpp_client-0.1.1.dist-info/LICENSE
whisper_cpp_client-0.1.1.dist-info/METADATA
whisper_cpp_client-0.1.1.dist-info/WHEEL
whisper_cpp_client-0.1.1.dist-info/top_level.txt
whisper_cpp_client-0.1.1.dist-info/RECORD
