Metadata-Version: 2.2
Name: whisper-cpp-client
Version: 0.1.1
Summary: A small, lightweight client for the whisper.cpp server.
Author-email: Chris Landa <stylesuxx@gmail.com>
License: MIT License
Project-URL: Homepage, https://github.com/stylesuxx/python-whisper-cpp-client
Project-URL: Issues, https://github.com/stylesuxx/python-whisper-cpp-client/issues
Classifier: Programming Language :: Python :: 3
Classifier: Operating System :: OS Independent
Requires-Python: >=3.8
License-File: LICENSE
Requires-Dist: requests
